coshed/__init__.py
coshed/bundy.py
coshed/calving.py
coshed/coshed_concat.py
coshed/coshed_config.py
coshed/coshed_html.py
coshed/coshed_watcher.py
coshed/defaults.py
coshed/flask_tools.py
coshed/git_changelog_helper.py
coshed/sassy_glue.py
coshed/stretchy_machine.py
coshed/swagger_glue.py
coshed/tools.py
coshed/utilities.py
coshed/vial.py
coshed/wolfication.py
coshed/wolfication_template_contents.py
coshed-0.13.1.dist-info/COPYING.txt
coshed-0.13.1.dist-info/METADATA
coshed-0.13.1.dist-info/WHEEL
coshed-0.13.1.dist-info/RECORD
