Metadata-Version: 2.1
Name: coshed
Version: 0.13.1
Summary: Project deployment and distribution tools for lazy developers
License: GPL-2.0-only
Author: doubleO8
Author-email: wb008@hdm-stuttgart.de
Requires-Python: >=3.8,<3.12
Classifier: License :: OSI Approved :: GNU General Public License v2 (GPLv2)
Classifier: Programming Language :: Python :: 3
Classifier: Programming Language :: Python :: 3.8
Classifier: Programming Language :: Python :: 3.9
Classifier: Programming Language :: Python :: 3.10
Classifier: Programming Language :: Python :: 3.11
Requires-Dist: Flask (>=3.0.2,<4.0.0)
Requires-Dist: Flask-Compress (>=1.14,<2.0)
Requires-Dist: Flask-Cors (>=4.0.0,<5.0.0)
Requires-Dist: beautifulsoup4 (>=4.6.0,<5.0.0)
Requires-Dist: cachelib (>=0.1)
Requires-Dist: flask-httpauth (>=4.8.0,<5.0.0)
Requires-Dist: future (>=0.18.2)
Requires-Dist: pendulum (>=2.1,<3.0)
Requires-Dist: requests (>=2.13.0)
Requires-Dist: six (>=1.13.0)
Requires-Dist: transitions (>=0.8.2,<0.9.0)
